<?xml version="1.0" encoding="utf-8" ?>
<dwsync>
<file name="archive_autoload.php" server="ftp.netsorrindo.com/www/intranet/" local="129479670480000000" remote="129703471200000000" />
<file name="authentication_autoload.php" server="ftp.netsorrindo.com/www/intranet/" local="129479670480000000" remote="129703471200000000" />
<file name="authentication_database_autoload.php" server="ftp.netsorrindo.com/www/intranet/" local="129479670480000000" remote="129703471200000000" />
<file name="authentication_openid_autoload.php" server="ftp.netsorrindo.com/www/intranet/" local="129479670480000000" remote="129703471200000000" />
<file name="base_autoload.php" server="ftp.netsorrindo.com/www/intranet/" local="129479670480000000" remote="129703471200000000" />
<file name="cache_autoload.php" server="ftp.netsorrindo.com/www/intranet/" local="129479670480000000" remote="129703471200000000" />
<file name="configuration_autoload.php" server="ftp.netsorrindo.com/www/intranet/" local="129479670480000000" remote="129703471200000000" />
<file name="console_autoload.php" server="ftp.netsorrindo.com/www/intranet/" local="129479670480000000" remote="129703471200000000" />
<file name="db_autoload.php" server="ftp.netsorrindo.com/www/intranet/" local="129479670480000000" remote="129703471200000000" />
<file name="db_schema_autoload.php" server="ftp.netsorrindo.com/www/intranet/" local="129479670480000000" remote="129703471200000000" />
<file name="debug_autoload.php" server="ftp.netsorrindo.com/www/intranet/" local="129479670480000000" remote="129703471200000000" />
<file name="document_autoload.php" server="ftp.netsorrindo.com/www/intranet/" local="129479670480000000" remote="129703471200000000" />
<file name="execution_autoload.php" server="ftp.netsorrindo.com/www/intranet/" local="129479670480000000" remote="129703471200000000" />
<file name="feed_autoload.php" server="ftp.netsorrindo.com/www/intranet/" local="129479670480000000" remote="129703471200000000" />
<file name="file_autoload.php" server="ftp.netsorrindo.com/www/intranet/" local="129479670480000000" remote="129703471200000000" />
<file name="graph_autoload.php" server="ftp.netsorrindo.com/www/intranet/" local="129479670480000000" remote="129703471200000000" />
<file name="graph_database_autoload.php" server="ftp.netsorrindo.com/www/intranet/" local="129479670480000000" remote="129703471200000000" />
<file name="image_analyzer_autoload.php" server="ftp.netsorrindo.com/www/intranet/" local="129479670480000000" remote="129703471200000000" />
<file name="image_autoload.php" server="ftp.netsorrindo.com/www/intranet/" local="129479670480000000" remote="129703471200000000" />
<file name="input_autoload.php" server="ftp.netsorrindo.com/www/intranet/" local="129479670480000000" remote="129703471200000000" />
<file name="log_autoload.php" server="ftp.netsorrindo.com/www/intranet/" local="129479670480000000" remote="129703471200000000" />
<file name="log_database_autoload.php" server="ftp.netsorrindo.com/www/intranet/" local="129479670480000000" remote="129703471200000000" />
<file name="mail_autoload.php" server="ftp.netsorrindo.com/www/intranet/" local="129479670480000000" remote="129703471200000000" />
<file name="mvc_authentication_autoload.php" server="ftp.netsorrindo.com/www/intranet/" local="129479670480000000" remote="129703471200000000" />
<file name="mvc_autoload.php" server="ftp.netsorrindo.com/www/intranet/" local="129479670480000000" remote="129703471200000000" />
<file name="mvc_feed_autoload.php" server="ftp.netsorrindo.com/www/intranet/" local="129479670480000000" remote="129703471800000000" />
<file name="mvc_mail_autoload.php" server="ftp.netsorrindo.com/www/intranet/" local="129479670480000000" remote="129703471800000000" />
<file name="mvc_template_autoload.php" server="ftp.netsorrindo.com/www/intranet/" local="129479670480000000" remote="129703471800000000" />
<file name="persistent_autoload.php" server="ftp.netsorrindo.com/www/intranet/" local="129479670480000000" remote="129703471800000000" />
<file name="persistent_object_autoload.php" server="ftp.netsorrindo.com/www/intranet/" local="129479670480000000" remote="129703471800000000" />
<file name="php_generator_autoload.php" server="ftp.netsorrindo.com/www/intranet/" local="129479670480000000" remote="129703471800000000" />
<file name="query_autoload.php" server="ftp.netsorrindo.com/www/intranet/" local="129479670480000000" remote="129703471800000000" />
<file name="search_autoload.php" server="ftp.netsorrindo.com/www/intranet/" local="129479670480000000" remote="129703471800000000" />
<file name="signal_autoload.php" server="ftp.netsorrindo.com/www/intranet/" local="129479670480000000" remote="129703471800000000" />
<file name="system_autoload.php" server="ftp.netsorrindo.com/www/intranet/" local="129479670480000000" remote="129703471800000000" />
<file name="template_autoload.php" server="ftp.netsorrindo.com/www/intranet/" local="129479670480000000" remote="129703471800000000" />
<file name="template_translation_autoload.php" server="ftp.netsorrindo.com/www/intranet/" local="129479670480000000" remote="129703471800000000" />
<file name="translation_autoload.php" server="ftp.netsorrindo.com/www/intranet/" local="129479670480000000" remote="129703471800000000" />
<file name="translation_cache_autoload.php" server="ftp.netsorrindo.com/www/intranet/" local="129479670480000000" remote="129703471800000000" />
<file name="tree_autoload.php" server="ftp.netsorrindo.com/www/intranet/" local="129479670480000000" remote="129703471800000000" />
<file name="tree_db_autoload.php" server="ftp.netsorrindo.com/www/intranet/" local="129479670480000000" remote="129703471800000000" />
<file name="tree_persistent_autoload.php" server="ftp.netsorrindo.com/www/intranet/" local="129479670480000000" remote="129703471800000000" />
<file name="url_autoload.php" server="ftp.netsorrindo.com/www/intranet/" local="129479670480000000" remote="129703471800000000" />
<file name="webdav_autoload.php" server="ftp.netsorrindo.com/www/intranet/" local="129479670480000000" remote="129703471800000000" />
<file name="workflow_autoload.php" server="ftp.netsorrindo.com/www/intranet/" local="129479670480000000" remote="129703471800000000" />
<file name="workflow_database_autoload.php" server="ftp.netsorrindo.com/www/intranet/" local="129479670480000000" remote="129703471800000000" />
<file name="workflow_event_autoload.php" server="ftp.netsorrindo.com/www/intranet/" local="129479670480000000" remote="129703471800000000" />
<file name="workflow_signal_autoload.php" server="ftp.netsorrindo.com/www/intranet/" local="129479670480000000" remote="129703471800000000" />
</dwsync>